kotti_docit-1.0.0.dist-info/top_level.txt
kotti_docit-1.0.0.dist-info/WHEEL
kotti_docit-1.0.0.dist-info/entry_points.txt
kotti_docit-1.0.0.dist-info/metadata.json
kotti_docit-1.0.0.dist-info/RECORD
kotti_docit-1.0.0.dist-info/DESCRIPTION.rst
kotti_docit-1.0.0.dist-info/METADATA
kotti_docit/fanstatic.pyc
kotti_docit/__init__.pyc
kotti_docit/__init__.py
kotti_docit/resources.py
kotti_docit/resources.pyc
kotti_docit/fanstatic.py
kotti_docit/static/styles.css
kotti_docit/static/styles.min.css
kotti_docit/static/scripts.min.js
kotti_docit/static/scripts.js
kotti_docit/tests/conftest.py
kotti_docit/tests/test_view.py
kotti_docit/tests/test_resources.py
kotti_docit/tests/test_functional.py
kotti_docit/templates/password-reset.pt
kotti_docit/templates/custom-content-default.pt
kotti_docit/templates/custom-content-alternative.pt
kotti_docit/locale/.gitkeep
kotti_docit/alembic/script.py.mako
kotti_docit/views/default.py
kotti_docit/views/view.py
kotti_docit/views/edit.py
kotti_docit/views/__init__.pyc
kotti_docit/views/__init__.py
kotti_docit/views/edit.pyc
kotti_docit/views/default.pyc
kotti_docit/views/view.pyc
