Metadata-Version: 2.0
Name: kotti-docit
Version: 1.0.0
Summary: Documentation site for your Kotti site
Home-page: https://github.com/b4oshany/kotti_docit
Author: Oshane Bailey
Author-email: b4.oshany@gmail.com
License: BSD-derived (http://www.repoze.org/LICENSE.txt)
Keywords: kotti web cms wcms pylons pyramid sqlalchemy bootstrap
Platform: UNKNOWN
Classifier: Programming Language :: Python
Classifier: Programming Language :: Python :: 2.7
Classifier: Framework :: Pylons
Classifier: Topic :: Internet :: WWW/HTTP
Classifier: Topic :: Internet :: WWW/HTTP :: Dynamic Content
Classifier: Topic :: Internet :: WWW/HTTP :: WSGI :: Application
Classifier: License :: Repoze Public License
Requires-Dist: Kotti (>=1.0.0)
Requires-Dist: kotti-tinymce
Requires-Dist: kotti-pdf (>=0.3.5)
Requires-Dist: kotti-alert (>=0.2.5)
Requires-Dist: click (>=6.6)
Requires-Dist: kotti-survey
Requires-Dist: kotti-contenttypes (>=0.1.0)
